Workbook
Name Slicer_Months__Order_Date: #N/A

Sheet Business Case
A1: Business Case and Project Brief
A3: Company | B3: DecisionMart Retail Ltd
A4: Background | B4: DecisionMart operates eight branches across Nigeria and sells food, beverages, household products, personal care items, electronics and office supplies.
A5: Problem | B5: Management has observed that revenue is improving, but profit margin is weakening. Fast-moving products are experiencing stock pressure while some slow-moving items remain overstocked.
A6: Your role | B6: You are the junior data analyst assigned to look into the data, investigate the causes, build an Excel dashboard and recommend practical actions.
A7: Audience | B7: Managing Director, Head of Sales, Branch Managers and Inventory Manager.
A8: Decision required | B8: Which products, branches and operational practices should management prioritise to improve profit and inventory efficiency?
A9: Deliverable | B9: A one-page or Multiple pages interactive Excel dashboard plus five evidence-based findings and recommendations.

Sheet Course
C9: Get This course on how to make money as a Data Analyst: https://datawithdecision.selar.com/a70371o75j

Sheet Product_Master
A1: Product ID | B1: Product Name | C1: Category | D1: Subcategory | E1: Brand | F1: Unit Cost | G1: Unit Price | H1: Reorder Level | I1: Opening Stock | J1: Stock Received | K1: Closing Stock | L1: Stock status
A2: P001 | B2: Golden Harvest Rice 5kg | C2: Food | D2: Grains | E2: Golden Harvest | F2: 14500 | G2: 17500 | H2: 60 | I2: 193 | J2: 88 | K2: 36 | L2: =IF(ProductMasterTable[[#This Row],[Closing Stock]]<ProductMasterTable[[#This Row],[Reorder Level]],"underStocked",IF(ProductMasterTable[[#This Row],[Closing Stock]]>3*ProductMasterTable[[#This Row],[Reorder Level]],"overStocked","Health")) -> underStocked
A3: P002 | B3: Mama's Pride Beans 2kg | C3: Food | D3: Grains | E3: Mama's Pride | F3: 6200 | G3: 7900 | H3: 45 | I3: 92 | J3: 107 | K3: 50 | L3: =IF(ProductMasterTable[[#This Row],[Closing Stock]]<ProductMasterTable[[#This Row],[Reorder Level]],"underStocked",IF(ProductMasterTable[[#This Row],[Closing Stock]]>3*ProductMasterTable[[#This Row],[Reorder Level]],"overStocked","Health")) -> Health
A4: P003 | B4: SunGold Vegetable Oil 2L | C4: Food | D4: Cooking Oil | E4: SunGold | F4: 7800 | G4: 9800 | H4: 50 | I4: 60 | J4: 238 | K4: 8 | L4: =IF(ProductMasterTable[[#This Row],[Closing Stock]]<ProductMasterTable[[#This Row],[Reorder Level]],"underStocked",IF(ProductMasterTable[[#This Row],[Closing Stock]]>3*ProductMasterTable[[#This Row],[Reorder Level]],"overStocked","Health")) -> underStocked
A5: P004 | B5: FreshDay Milk 1L | C5: Beverages | D5: Dairy | E5: FreshDay | F5: 1650 | G5: 2200 | H5: 70 | I5: 208 | J5: 349 | K5: 57 | L5: =IF(ProductMasterTable[[#This Row],[Closing Stock]]<ProductMasterTable[[#This Row],[Reorder Level]],"underStocked",IF(ProductMasterTable[[#This Row],[Closing Stock]]>3*ProductMasterTable[[#This Row],[Reorder Level]],"overStocked","Health")) -> underStocked
A6: P005 | B6: CrispyBite Biscuits Pack | C6: Food | D6: Snacks | E6: CrispyBite | F6: 850 | G6: 1300 | H6: 90 | I6: 347 | J6: 306 | K6: 53 | L6: =IF(ProductMasterTable[[#This Row],[Closing Stock]]<ProductMasterTable[[#This Row],[Reorder Level]],"underStocked",IF(ProductMasterTable[[#This Row],[Closing Stock]]>3*ProductMasterTable[[#This Row],[Reorder Level]],"overStocked","Health")) -> underStocked
A7: P006 | B7: AquaPure Water 75cl | C7: Beverages | D7: Water | E7: AquaPure | F7: 230 | G7: 400 | H7: 150 | I7: 105 | J7: 245 | K7: 57 | L7: =IF(ProductMasterTable[[#This Row],[Closing Stock]]<ProductMasterTable[[#This Row],[Reorder Level]],"underStocked",IF(ProductMasterTable[[#This Row],[Closing Stock]]>3*ProductMasterTable[[#This Row],[Reorder Level]],"overStocked","Health")) -> underStocked
A8: P007 | B8: Naija Malt Can | C8: Beverages | D8: Malt | E8: Naija Malt | F8: 550 | G8: 850 | H8: 100 | I8: 169 | J8: 358 | K8: 204 | L8: =IF(ProductMasterTable[[#This Row],[Closing Stock]]<ProductMasterTable[[#This Row],[Reorder Level]],"underStocked",IF(ProductMasterTable[[#This Row],[Closing Stock]]>3*ProductMasterTable[[#This Row],[Reorder Level]],"overStocked","Health")) -> Health
A9: P008 | B9: Sparkle Cola 50cl | C9: Beverages | D9: Soft Drinks | E9: Sparkle | F9: 330 | G9: 550 | H9: 120 | I9: 73 | J9: 407 | K9: 161 | L9: =IF(ProductMasterTable[[#This Row],[Closing Stock]]<ProductMasterTable[[#This Row],[Reorder Level]],"underStocked",IF(ProductMasterTable[[#This Row],[Closing Stock]]>3*ProductMasterTable[[#This Row],[Reorder Level]],"overStocked","Health")) -> Health
A10: P009 | B10: BrightWash Detergent 1kg | C10: Household | D10: Cleaning | E10: BrightWash | F10: 2400 | G10: 3400 | H10: 55 | I10: 210 | J10: 221 | K10: 134 | L10: =IF(ProductMasterTable[[#This Row],[Closing Stock]]<ProductMasterTable[[#This Row],[Reorder Level]],"underStocked",IF(ProductMasterTable[[#This Row],[Closing Stock]]>3*ProductMasterTable[[#This Row],[Reorder Level]],"overStocked","Health")) -> Health
A11: P010 | B11: SoftCare Tissue 10 Rolls | C11: Household | D11: Paper Products | E11: SoftCare | F11: 3200 | G11: 4500 | H11: 45 | I11: 78 | J11: 159 | K11: 97 | L11: =IF(ProductMasterTable[[#This Row],[Closing Stock]]<ProductMasterTable[[#This Row],[Reorder Level]],"underStocked",IF(ProductMasterTable[[#This Row],[Closing Stock]]>3*ProductMasterTable[[#This Row],[Reorder Level]],"overStocked","Health")) -> Health
A12: P011 | B12: CleanPro Disinfectant 1L | C12: Household | D12: Cleaning | E12: CleanPro | F12: 2800 | G12: 3900 | H12: 40 | I12: 91 | J12: 41 | K12: 117 | L12: =IF(ProductMasterTable[[#This Row],[Closing Stock]]<ProductMasterTable[[#This Row],[Reorder Level]],"underStocked",IF(ProductMasterTable[[#This Row],[Closing Stock]]>3*ProductMasterTable[[#This Row],[Reorder Level]],"overStocked","Health")) -> Health
A13: P012 | B13: HomeFresh Air Freshener | C13: Household | D13: Home Care | E13: HomeFresh | F13: 1700 | G13: 2600 | H13: 35 | I13: 120 | J13: 75 | K13: 194 | L13: =IF(ProductMasterTable[[#This Row],[Closing Stock]]<ProductMasterTable[[#This Row],[Reorder Level]],"underStocked",IF(ProductMasterTable[[#This Row],[Closing Stock]]>3*ProductMasterTable[[#This Row],[Reorder Level]],"overStocked","Health")) -> overStocked
... A25: P024 | B25: ErgoDesk Mouse Pad | C25: Office Supplies | D25: Accessories | E25: ErgoDesk | F25: 1700 | G25: 2800 | H25: 30 | I25: 44 | J25: 140 | K25: 102 | L25: =IF(ProductMasterTable[[#This Row],[Closing Stock]]<ProductMasterTable[[#This Row],[Reorder Level]],"underStocked",IF(ProductMasterTable[[#This Row],[Closing Stock]]>3*ProductMasterTable[[#This Row],[Reorder Level]],"overStocked","Health")) -> overStocked

Sheet Branch_Master
A1: Branch ID | B1: Branch Name | C1: State | D1: Region | E1: Location Type
A2: B01 | B2: Wuse Central | C2: Abuja | D2: North Central | E2: Urban
A3: B02 | B3: Garki Market | C3: Abuja | D3: North Central | E3: Urban
A4: B03 | B4: Ikeja City | C4: Lagos | D4: South West | E4: Urban
A5: B04 | B5: Lekki Mall | C5: Lagos | D5: South West | E5: Urban
A6: B05 | B6: Kano Central | C6: Kano | D6: North West | E6: Urban
A7: B06 | B7: Port Harcourt Hub | C7: Rivers | D7: South South | E7: Urban
A8: B07 | B8: Enugu Main | C8: Enugu | D8: South East | E8: Urban
A9: B08 | B9: Ilorin Retail | C9: Kwara | D9: North Central | E9: Semi-Urban

Sheet Sales_Clean_Reference
A1: Order ID | B1: Order Date | C1: Product ID | D1: Product Name | E1: Category | F1: Subcategory | G1: Brand | H1: Branch ID | I1: Branch Name | J1: State | K1: Region | L1: Customer Type | M1: Payment Method | N1: Quantity | O1: Unit Cost | P1: Unit Price | Q1: Discount % | R1: Supplier | S1: Delivery Days | T1: Gross Sales | U1: Discount Amount | V1: Net Revenue | W1: Total Cost | X1: Profit | Y1: Profit Margin | Z1: Inventory Status | AA1: Discount Impact | AB1: Max Allowed Discount | AC1: Column1 | AD1: Unit Margin | AE1: Unit Margin %
A2: ORD-10001 | B2: 45852 | C2: P006 | D2: AquaPure Water 75cl | E2: Beverages | F2: Water | G2: AquaPure | H2: B05 | I2: Kano Central | J2: Kano | K2: North West | L2: Walk-in | M2: Card | N2: 2 | O2: 230 | P2: 400 | Q2: 0.05 | R2: Metro Drinks | S2: 11 | T2: 800 | U2: 40 | V2: 760 | W2: 460 | X2: 300 | Y2: 0.39473684 | Z2: Understocked | AA2: =IF(AND(SalesCleanTable[[#This Row],[Discount %]]>0, SalesCleanTable[[#This Row],[Profit]]<0), "Discount loss", "Safe") -> Safe | AB2: =(SalesCleanTable[[#This Row],[Unit Price]] - SalesCleanTable[[#This Row],[Unit Cost]]) / SalesCleanTable[[#This Row],[Unit Price]] -> 0.425 | AC2: =IF(SalesCleanTable[[#This Row],[Discount %]] > SalesCleanTable[[#This Row],[Max Allowed Discount]], "Discount loss", "Safe") -> Safe | AD2: =SalesCleanTable[[#This Row],[Unit Price]] - SalesCleanTable[[#This Row],[Unit Cost]] -> 170 | AE2: =(SalesCleanTable[[#This Row],[Unit Price]] - SalesCleanTable[[#This Row],[Unit Cost]]) / SalesCleanTable[[#This Row],[Unit Price]] -> 0.425
A3: ORD-10002 | B3: 45983 | C3: P004 | D3: FreshDay Milk 1L | E3: Beverages | F3: Dairy | G3: FreshDay | H3: B06 | I3: Port Harcourt Hub | J3: Rivers | K3: South South | L3: Corporate | M3: POS | N3: 1 | O3: 1650 | P3: 2200 | Q3: 0.05 | R3: Metro Drinks | S3: 4 | T3: 2200 | U3: 110 | V3: 2090 | W3: 1650 | X3: 440 | Y3: 0.21052632 | Z3: Understocked | AA3: =IF(AND(SalesCleanTable[[#This Row],[Discount %]]>0, SalesCleanTable[[#This Row],[Profit]]<0), "Discount loss", "Safe") -> Safe | AB3: =(SalesCleanTable[[#This Row],[Unit Price]] - SalesCleanTable[[#This Row],[Unit Cost]]) / SalesCleanTable[[#This Row],[Unit Price]] -> 0.25 | AC3: =IF(SalesCleanTable[[#This Row],[Discount %]] > SalesCleanTable[[#This Row],[Max Allowed Discount]], "Discount loss", "Safe") -> Safe | AD3: =SalesCleanTable[[#This Row],[Unit Price]] - SalesCleanTable[[#This Row],[Unit Cost]] -> 550 | AE3: =(SalesCleanTable[[#This Row],[Unit Price]] - SalesCleanTable[[#This Row],[Unit Cost]]) / SalesCleanTable[[#This Row],[Unit Price]] -> 0.25
A4: ORD-10003 | B4: 45686 | C4: P005 | D4: CrispyBite Biscuits Pack | E4: Food | F4: Snacks | G4: CrispyBite | H4: B01 | I4: Wuse Central | J4: Abuja | K4: North Central | L4: Walk-in | M4: POS | N4: 2 | O4: 850 | P4: 1300 | Q4: 0 | R4: Prime Grocery Ltd | S4: 6 | T4: 2600 | U4: 0 | V4: 2600 | W4: 1700 | X4: 900 | Y4: 0.34615385 | Z4: Understocked | AA4: =IF(AND(SalesCleanTable[[#This Row],[Discount %]]>0, SalesCleanTable[[#This Row],[Profit]]<0), "Discount loss", "Safe") -> Safe | AB4: =(SalesCleanTable[[#This Row],[Unit Price]] - SalesCleanTable[[#This Row],[Unit Cost]]) / SalesCleanTable[[#This Row],[Unit Price]] -> 0.34615385 | AC4: =IF(SalesCleanTable[[#This Row],[Discount %]] > SalesCleanTable[[#This Row],[Max Allowed Discount]], "Discount loss", "Safe") -> Safe | AD4: =SalesCleanTable[[#This Row],[Unit Price]] - SalesCleanTable[[#This Row],[Unit Cost]] -> 450 | AE4: =(SalesCleanTable[[#This Row],[Unit Price]] - SalesCleanTable[[#This Row],[Unit Cost]]) / SalesCleanTable[[#This Row],[Unit Price]] -> 0.34615385
A5: ORD-10004 | B5: 45913 | C5: P007 | D5: Naija Malt Can | E5: Beverages | F5: Malt | G5: Naija Malt | H5: B07 | I5: Enugu Main | J5: Enugu | K5: South East | L5: Walk-in | M5: POS | N5: 2 | O5: 550 | P5: 850 | Q5: 0 | R5: Refresh Nigeria | S5: 12 | T5: 1700 | U5: 0 | V5: 1700 | W5: 1100 | X5: 600 | Y5: 0.35294118 | Z5: Healthy | AA5: =IF(AND(SalesCleanTable[[#This Row],[Discount %]]>0, SalesCleanTable[[#This Row],[Profit]]<0), "Discount loss", "Safe") -> Safe | AB5: =(SalesCleanTable[[#This Row],[Unit Price]] - SalesCleanTable[[#This Row],[Unit Cost]]) / SalesCleanTable[[#This Row],[Unit Price]] -> 0.35294118 | AC5: =IF(SalesCleanTable[[#This Row],[Discount %]] > SalesCleanTable[[#This Row],[Max Allowed Discount]], "Discount loss", "Safe") -> Safe | AD5: =SalesCleanTable[[#This Row],[Unit Price]] - SalesCleanTable[[#This Row],[Unit Cost]] -> 300 | AE5: =(SalesCleanTable[[#This Row],[Unit Price]] - SalesCleanTable[[#This Row],[Unit Cost]]) / SalesCleanTable[[#This Row],[Unit Price]] -> 0.35294118
A6: ORD-10005 | B6: 45956 | C6: P007 | D6: Naija Malt Can | E6: Beverages | F6: Malt | G6: Naija Malt | H6: B02 | I6: Garki Market | J6: Abuja | K6: North Central | L6: Walk-in | M6: Cash | N6: 10 | O6: 550 | P6: 850 | Q6: 0.05 | R6: BlueWave Distributors | S6: 3 | T6: 8500 | U6: 425 | V6: 8075 | W6: 5500 | X6: 2575 | Y6: 0.31888545 | Z6: Healthy | AA6: =IF(AND(SalesCleanTable[[#This Row],[Discount %]]>0, SalesCleanTable[[#This Row],[Profit]]<0), "Discount loss", "Safe") -> Safe | AB6: =(SalesCleanTable[[#This Row],[Unit Price]] - SalesCleanTable[[#This Row],[Unit Cost]]) / SalesCleanTable[[#This Row],[Unit Price]] -> 0.35294118 | AC6: =IF(SalesCleanTable[[#This Row],[Discount %]] > SalesCleanTable[[#This Row],[Max Allowed Discount]], "Discount loss", "Safe") -> Safe | AD6: =SalesCleanTable[[#This Row],[Unit Price]] - SalesCleanTable[[#This Row],[Unit Cost]] -> 300 | AE6: =(SalesCleanTable[[#This Row],[Unit Price]] - SalesCleanTable[[#This Row],[Unit Cost]]) / SalesCleanTable[[#This Row],[Unit Price]] -> 0.35294118
A7: ORD-10006 | B7: 46006 | C7: P008 | D7: Sparkle Cola 50cl | E7: Beverages | F7: Soft Drinks | G7: Sparkle | H7: B01 | I7: Wuse Central | J7: Abuja | K7: North Central | L7: Walk-in | M7: POS | N7: 2 | O7: 330 | P7: 550 | Q7: 0.2 | R7: BlueWave Distributors | S7: 11 | T7: 1100 | U7: 220 | V7: 880 | W7: 660 | X7: 220 | Y7: 0.25 | Z7: Healthy | AA7: =IF(AND(SalesCleanTable[[#This Row],[Discount %]]>0, SalesCleanTable[[#This Row],[Profit]]<0), "Discount loss", "Safe") -> Safe | AB7: =(SalesCleanTable[[#This Row],[Unit Price]] - SalesCleanTable[[#This Row],[Unit Cost]]) / SalesCleanTable[[#This Row],[Unit Price]] -> 0.4 | AC7: =IF(SalesCleanTable[[#This Row],[Discount %]] > SalesCleanTable[[#This Row],[Max Allowed Discount]], "Discount loss", "Safe") -> Safe | AD7: =SalesCleanTable[[#This Row],[Unit Price]] - SalesCleanTable[[#This Row],[Unit Cost]] -> 220 | AE7: =(SalesCleanTable[[#This Row],[Unit Price]] - SalesCleanTable[[#This Row],[Unit Cost]]) / SalesCleanTable[[#This Row],[Unit Price]] -> 0.4
A8: ORD-10007 | B8: 46007 | C8: P020 | D8: Luma LED Bulb 12W | E8: Electronics | F8: Lighting | G8: Luma | H8: B06 | I8: Port Harcourt Hub | J8: Rivers | K8: South South | L8: Walk-in | M8: Cash | N8: 4 | O8: 1500 | P8: 2500 | Q8: 0.05 | R8: TechBridge Africa | S8: 12 | T8: 10000 | U8: 500 | V8: 9500 | W8: 6000 | X8: 3500 | Y8: 0.36842105 | Z8: Healthy | AA8: =IF(AND(SalesCleanTable[[#This Row],[Discount %]]>0, SalesCleanTable[[#This Row],[Profit]]<0), "Discount loss", "Safe") -> Safe | AB8: =(SalesCleanTable[[#This Row],[Unit Price]] - SalesCleanTable[[#This Row],[Unit Cost]]) / SalesCleanTable[[#This Row],[Unit Price]] -> 0.4 | AC8: =IF(SalesCleanTable[[#This Row],[Discount %]] > SalesCleanTable[[#This Row],[Max Allowed Discount]], "Discount loss", "Safe") -> Safe | AD8: =SalesCleanTable[[#This Row],[Unit Price]] - SalesCleanTable[[#This Row],[Unit Cost]] -> 1000 | AE8: =(SalesCleanTable[[#This Row],[Unit Price]] - SalesCleanTable[[#This Row],[Unit Cost]]) / SalesCleanTable[[#This Row],[Unit Price]] -> 0.4
A9: ORD-10008 | B9: 45792 | C9: P023 | D9: StudyPro Notebook Pack | E9: Office Supplies | F9: Stationery | G9: StudyPro | H9: B06 | I9: Port Harcourt Hub | J9: Rivers | K9: South South | L9: Member | M9: POS | N9: 3 | O9: 2800 | P9: 4200 | Q9: 0 | R9: Metro Stationery | S9: 10 | T9: 12600 | U9: 0 | V9: 12600 | W9: 8400 | X9: 4200 | Y9: 0.33333333 | Z9: Understocked | AA9: =IF(AND(SalesCleanTable[[#This Row],[Discount %]]>0, SalesCleanTable[[#This Row],[Profit]]<0), "Discount loss", "Safe") -> Safe | AB9: =(SalesCleanTable[[#This Row],[Unit Price]] - SalesCleanTable[[#This Row],[Unit Cost]]) / SalesCleanTable[[#This Row],[Unit Price]] -> 0.33333333 | AC9: =IF(SalesCleanTable[[#This Row],[Discount %]] > SalesCleanTable[[#This Row],[Max Allowed Discount]], "Discount loss", "Safe") -> Safe | AD9: =SalesCleanTable[[#This Row],[Unit Price]] - SalesCleanTable[[#This Row],[Unit Cost]] -> 1400 | AE9: =(SalesCleanTable[[#This Row],[Unit Price]] - SalesCleanTable[[#This Row],[Unit Cost]]) / SalesCleanTable[[#This Row],[Unit Price]] -> 0.33333333
A10: ORD-10009 | B10: 45849 | C10: P016 | D10: RoyalScent Perfume 50ml | E10: Personal Care | F10: Fragrance | G10: RoyalScent | H10: B04 | I10: Lekki Mall | J10: Lagos | K10: South West | L10: Walk-in | M10: Transfer | N10: 5 | O10: 8500 | P10: 12500 | Q10: 0.15 | R10: CarePlus Wholesale | S10: 2 | T10: 62500 | U10: 9375 | V10: 53125 | W10: 42500 | X10: 10625 | Y10: 0.2 | Z10: Overstocked | AA10: =IF(AND(SalesCleanTable[[#This Row],[Discount %]]>0, SalesCleanTable[[#This Row],[Profit]]<0), "Discount loss", "Safe") -> Safe | AB10: =(SalesCleanTable[[#This Row],[Unit Price]] - SalesCleanTable[[#This Row],[Unit Cost]]) / SalesCleanTable[[#This Row],[Unit Price]] -> 0.32 | AC10: =IF(SalesCleanTable[[#This Row],[Discount %]] > SalesCleanTable[[#This Row],[Max Allowed Discount]], "Discount loss", "Safe") -> Safe | AD10: =SalesCleanTable[[#This Row],[Unit Price]] - SalesCleanTable[[#This Row],[Unit Cost]] -> 4000 | AE10: =(SalesCleanTable[[#This Row],[Unit Price]] - SalesCleanTable[[#This Row],[Unit Cost]]) / SalesCleanTable[[#This Row],[Unit Price]] -> 0.32
A11: ORD-10010 | B11: 45815 | C11: P005 | D11: CrispyBite Biscuits Pack | E11: Food | F11: Snacks | G11: CrispyBite | H11: B02 | I11: Garki Market | J11: Abuja | K11: North Central | L11: Member | M11: POS | N11: 3 | O11: 850 | P11: 1300 | Q11: 0 | R11: Prime Grocery Ltd | S11: 13 | T11: 3900 | U11: 0 | V11: 3900 | W11: 2550 | X11: 1350 | Y11: 0.34615385 | Z11: Understocked | AA11: =IF(AND(SalesCleanTable[[#This Row],[Discount %]]>0, SalesCleanTable[[#This Row],[Profit]]<0), "Discount loss", "Safe") -> Safe | AB11: =(SalesCleanTable[[#This Row],[Unit Price]] - SalesCleanTable[[#This Row],[Unit Cost]]) / SalesCleanTable[[#This Row],[Unit Price]] -> 0.34615385 | AC11: =IF(SalesCleanTable[[#This Row],[Discount %]] > SalesCleanTable[[#This Row],[Max Allowed Discount]], "Discount loss", "Safe") -> Safe | AD11: =SalesCleanTable[[#This Row],[Unit Price]] - SalesCleanTable[[#This Row],[Unit Cost]] -> 450 | AE11: =(SalesCleanTable[[#This Row],[Unit Price]] - SalesCleanTable[[#This Row],[Unit Cost]]) / SalesCleanTable[[#This Row],[Unit Price]] -> 0.34615385
A12: ORD-10011 | B12: 45995 | C12: P008 | D12: Sparkle Cola 50cl | E12: Beverages | F12: Soft Drinks | G12: Sparkle | H12: B04 | I12: Lekki Mall | J12: Lagos | K12: South West | L12: Walk-in | M12: Card | N12: 2 | O12: 330 | P12: 550 | Q12: 0.15 | R12: Metro Drinks | S12: 13 | T12: 1100 | U12: 165 | V12: 935 | W12: 660 | X12: 275 | Y12: 0.29411765 | Z12: Healthy | AA12: =IF(AND(SalesCleanTable[[#This Row],[Discount %]]>0, SalesCleanTable[[#This Row],[Profit]]<0), "Discount loss", "Safe") -> Safe | AB12: =(SalesCleanTable[[#This Row],[Unit Price]] - SalesCleanTable[[#This Row],[Unit Cost]]) / SalesCleanTable[[#This Row],[Unit Price]] -> 0.4 | AC12: =IF(SalesCleanTable[[#This Row],[Discount %]] > SalesCleanTable[[#This Row],[Max Allowed Discount]], "Discount loss", "Safe") -> Safe | AD12: =SalesCleanTable[[#This Row],[Unit Price]] - SalesCleanTable[[#This Row],[Unit Cost]] -> 220 | AE12: =(SalesCleanTable[[#This Row],[Unit Price]] - SalesCleanTable[[#This Row],[Unit Cost]]) / SalesCleanTable[[#This Row],[Unit Price]] -> 0.4
A13: ORD-10012 | B13: 45760 | C13: P015 | D13: SilkyTouch Bath Soap | E13: Personal Care | F13: Bath | G13: SilkyTouch | H13: B03 | I13: Ikeja City | J13: Lagos | K13: South West | L13: Member | M13: Transfer | N13: 4 | O13: 600 | P13: 950 | Q13: 0.05 | R13: CarePlus Wholesale | S13: 4 | T13: 3800 | U13: 190 | V13: 3610 | W13: 2400 | X13: 1210 | Y13: 0.33518006 | Z13: Healthy | AA13: =IF(AND(SalesCleanTable[[#This Row],[Discount %]]>0, SalesCleanTable[[#This Row],[Profit]]<0), "Discount loss", "Safe") -> Safe | AB13: =(SalesCleanTable[[#This Row],[Unit Price]] - SalesCleanTable[[#This Row],[Unit Cost]]) / SalesCleanTable[[#This Row],[Unit Price]] -> 0.36842105 | AC13: =IF(SalesCleanTable[[#This Row],[Discount %]] > SalesCleanTable[[#This Row],[Max Allowed Discount]], "Discount loss", "Safe") -> Safe | AD13: =SalesCleanTable[[#This Row],[Unit Price]] - SalesCleanTable[[#This Row],[Unit Cost]] -> 350 | AE13: =(SalesCleanTable[[#This Row],[Unit Price]] - SalesCleanTable[[#This Row],[Unit Cost]]) / SalesCleanTable[[#This Row],[Unit Price]] -> 0.36842105
... A2802: ORD-11239 | B2802: 45717 | C2802: P018 | D2802: VoltSafe Power Bank 20k | E2802: Electronics | F2802: Mobile Accessories | G2802: VoltSafe | H2802: B04 | I2802: Lekki Mall | J2802: Lagos | K2802: South West | L2802: Walk-in | M2802: POS | N2802: 10 | O2802: 18000 | P2802: 24500 | Q2802: 0.1 | R2802: VoltEdge Ltd | S2802: 13 | T2802: 245000 | U2802: 24500 | V2802: 220500 | W2802: 180000 | X2802: 40500 | Y2802: 0.18367347 | Z2802: Understocked | AA2802: =IF(AND(SalesCleanTable[[#This Row],[Discount %]]>0, SalesCleanTable[[#This Row],[Profit]]<0), "Discount loss", "Safe") -> Safe | AB2802: =(SalesCleanTable[[#This Row],[Unit Price]] - SalesCleanTable[[#This Row],[Unit Cost]]) / SalesCleanTable[[#This Row],[Unit Price]] -> 0.26530612 | AC2802: =IF(SalesCleanTable[[#This Row],[Discount %]] > SalesCleanTable[[#This Row],[Max Allowed Discount]], "Discount loss", "Safe") -> Safe | AD2802: =SalesCleanTable[[#This Row],[Unit Price]] - SalesCleanTable[[#This Row],[Unit Cost]] -> 6500 | AE2802: =(SalesCleanTable[[#This Row],[Unit Price]] - SalesCleanTable[[#This Row],[Unit Cost]]) / SalesCleanTable[[#This Row],[Unit Price]] -> 0.26530612

Sheet pivot table
A3: Sum of Net Revenue | B3: Sum of Profit | C3: Average of Profit Margin | D3: Count of Product Name | E3: Sum of Total Cost
A4: 39764008 | B4: 8091717.5 | C4: 0.26395211 | D4: 2801 | E4: 31672290 | I4: Months (Order Date) | J4: Helper | K4: Months (Order Date) | L4: Sum of Net Revenue | M4: Sum of Profit | N4: margin | O4: mom Revenue GR | Q4: Months (Order Date) | AG4: Months | AH4: Net Revenue | AI4: Profit | AJ4: margin2 | AN4: Branch Name | AO4: Profit | AP4: Net Revenue | AU4: Region | AV4: Net Revenue | AW4: Profit | BC4: Row Labels | BD4: Count of Stock status | BI4: Product Name | BJ4: Net Revenue | BK4: Profit | BL4: Sum of Quantity | BN4: profit margin | BO4: inventory status | BP4: Revenue | BQ4: margin understocked | BR4: Qty understocked | BS4: margin Health | BT4: Qty Health | BU4: margin over stocked | BV4: Qty overstocked | CA4: Product Name | CB4: Net Revenue | CE4: total revenuo
I5: Jan | J5: 1 | K5: Jan | L5: 3164650 | M5: 600700 | N5: =M5/L5 -> 0.18981562 | Q5: Jan | AG5: Jan | AH5: 3164650 | AI5: 600700 | AJ5: 0.18981562 | AN5: Ikeja City | AO5: 1609720 | AP5: 7802760 | AQ5: =AO5/AP5 -> 0.20630136 | AU5: South West | AV5: 13966085 | AW5: 2882795 | BC5: Health | BD5: 11 | BI5: AquaPure Water 75cl | BJ5: 295440 | BK5: 111670 | BL5: 799 | BN5: =BK5/BJ5 -> 0.37797861 | BO5: =_xlfn.XLOOKUP(BI5,ProductMasterTable[Product Name],ProductMasterTable[Stock status],) -> underStocked | BP5: =BJ5 -> 295440 | BQ5: =IF(BO5="underStocked",BN5,NA()) -> 0.37797861 | BR5: =IF(BO5="underStocked",BL5,NA()) -> 799 | BS5: =IF(BO5="Health",BN5,NA()) -> #N/A | BT5: =IF(BO5="Health",BL5,NA()) -> #N/A | BU5: =IF(BO5="overStocked",BN5,NA()) -> #N/A | BV5: =IF(BO5="overStocked",BL5,NA()) -> #N/A | CA5: Golden Harvest Rice 5kg | CB5: 7868875 | CE5: =A4 -> 39764008 | CY5: Months
I6: Feb | J6: 2 | K6: Feb | L6: 3119687.5 | M6: 613917.5 | N6: =M6/L6 -> 0.19678814 | O6: =(L6-L5)/L5 -> -0.014207732 | Q6: Feb | S6: count of months | AG6: Feb | AH6: 3119687.5 | AI6: 613917.5 | AJ6: 0.19678814 | AN6: Lekki Mall | AO6: 1273075 | AP6: 6163325 | AQ6: =AO6/AP6 -> 0.20655653 | AU6: North Central | AV6: 13049302 | AW6: 2595962.5 | BC6: overStocked | BD6: 4 | BI6: BrightWash Detergent 1kg | BJ6: 1248310 | BK6: 307510 | BL6: 392 | BN6: =BK6/BJ6 -> 0.24634105 | BO6: =_xlfn.XLOOKUP(BI6,ProductMasterTable[Product Name],ProductMasterTable[Stock status],) -> Health | BP6: =BJ6 -> 1248310 | BQ6: =IF(BO6="underStocked",BN6,NA()) -> #N/A | BR6: =IF(BO6="underStocked",BL6,NA()) -> #N/A | BS6: =IF(BO6="Health",BN6,NA()) -> 0.24634105 | BT6: =IF(BO6="Health",BL6,NA()) -> 392 | BU6: =IF(BO6="overStocked",BN6,NA()) -> #N/A | BV6: =IF(BO6="overStocked",BL6,NA()) -> #N/A | CA6: Mama's Pride Beans 2kg | CB6: 2005020 | CX6: Supplier | CY6: Jan | CZ6: Feb | DA6: Mar | DB6: Apr | DC6: May | DD6: Jun | DE6: Jul | DF6: Aug | DG6: Sep | DH6: Oct | DI6: Nov | DJ6: Dec
I7: Mar | J7: 3 | K7: Mar | L7: 4116052.5 | M7: 805362.5 | N7: =M7/L7 -> 0.19566381 | O7: =(L7-L6)/L6 -> 0.31937975 | Q7: Mar | S7: =COUNTA(Q5:Q16) -> 12 | AG7: Mar | AH7: 4116052.5 | AI7: 805362.5 | AJ7: 0.19566381 | AN7: Wuse Central | AO7: 1209210 | AP7: 5842100 | AQ7: =AO7/AP7 -> 0.20698208 | AU7: South East | AV7: 4762662.5 | AW7: 991822.5 | BC7: underStocked | BD7: 9 | BI7: CleanPro Disinfectant 1L | BJ7: 935025 | BK7: 218225 | BL7: 256 | BN7: =BK7/BJ7 -> 0.23338948 | BO7: =_xlfn.XLOOKUP(BI7,ProductMasterTable[Product Name],ProductMasterTable[Stock status],) -> Health | BP7: =BJ7 -> 935025 | BQ7: =IF(BO7="underStocked",BN7,NA()) -> #N/A | BR7: =IF(BO7="underStocked",BL7,NA()) -> #N/A | BS7: =IF(BO7="Health",BN7,NA()) -> 0.23338948 | BT7: =IF(BO7="Health",BL7,NA()) -> 256 | BU7: =IF(BO7="overStocked",BN7,NA()) -> #N/A | BV7: =IF(BO7="overStocked",BL7,NA()) -> #N/A | CA7: SoundBeat Earbuds | CB7: 3438225 | CN7: Correlation discount & profit margin | CX7: AgroLink Nigeria
C8: docx | D8: value | E8: formatting | I8: Apr | J8: 4 | K8: Apr | L8: 3081370 | M8: 676200 | N8: =M8/L8 -> 0.21944784 | O8: =(L8-L7)/L7 -> -0.25137738 | Q8: Apr | AG8: Apr | AH8: 3081370 | AI8: 676200 | AJ8: 0.21944784 | AN8: Enugu Main | AO8: 991822.5 | AP8: 4762662.5 | AQ8: =AO8/AP8 -> 0.20824959 | AU8: South South | AV8: 4532182.5 | AW8: 905972.5 | BC8: Grand Total | BD8: 24 | BI8: CrispyBite Biscuits Pack | BJ8: 572455 | BK8: 166155 | BL8: 478 | BN8: =BK8/BJ8 -> 0.29024989 | BO8: =_xlfn.XLOOKUP(BI8,ProductMasterTable[Product Name],ProductMasterTable[Stock status],) -> underStocked | BP8: =BJ8 -> 572455 | BQ8: =IF(BO8="underStocked",BN8,NA()) -> 0.29024989 | BR8: =IF(BO8="underStocked",BL8,NA()) -> 478 | BS8: =IF(BO8="Health",BN8,NA()) -> #N/A | BT8: =IF(BO8="Health",BL8,NA()) -> #N/A | BU8: =IF(BO8="overStocked",BN8,NA()) -> #N/A | BV8: =IF(BO8="overStocked",BL8,NA()) -> #N/A | CA8: SunGold Vegetable Oil 2L | CB8: 4767210 | CE8: Top 5 | CF8: =SUM(CB5:CB9) -> 24885430 | CH8: precntge share | CI8: =CF8/CE5 -> 0.62582802 | CN8: =CORREL(Sales_Clean_Reference!Q:Q,Sales_Clean_Reference!Y:Y) -> -0.55334855 | CX8: BeautyHub Distribution
C9: Net Revenue | D9: =GETPIVOTDATA("Sum of Net Revenue",$A$3) -> 39764008 | E9: =IF(D9>=1000000000, "$" & TEXT(D9/1000000000, "0.0") & "B", IF(D9>=1000000, "$" &TEXT(D9/1000000, "0.0") & "M", IF(D9>=1000, "$" &TEXT(D9/1000, "0.0") & "K", "$" &TEXT(D9, "0.0")))) -> $39.8M | F9: blue | I9: May | J9: 5 | K9: May | L9: 2862620 | M9: 606430 | N9: =M9/L9 -> 0.21184439 | O9: =(L9-L8)/L8 -> -0.07099115 | Q9: May | S9: current month postion | AG9: May | AH9: 2862620 | AI9: 606430 | AJ9: 0.21184439 | AN9: Port Harcourt Hub | AO9: 905972.5 | AP9: 4532182.5 | AQ9: =AO9/AP9 -> 0.19989762 | AU9: North West | AV9: 3453775 | AW9: 715165 | BI9: ErgoDesk Mouse Pad | BJ9: 350000 | BK9: 101800 | BL9: 146 | BN9: =BK9/BJ9 -> 0.29085714 | BO9: =_xlfn.XLOOKUP(BI9,ProductMasterTable[Product Name],ProductMasterTable[Stock status],) -> overStocked | BP9: =BJ9 -> 350000 | BQ9: =IF(BO9="underStocked",BN9,NA()) -> #N/A | BR9: =IF(BO9="underStocked",BL9,NA()) -> #N/A | BS9: =IF(BO9="Health",BN9,NA()) -> #N/A | BT9: =IF(BO9="Health",BL9,NA()) -> #N/A | BU9: =IF(BO9="overStocked",BN9,NA()) -> 0.29085714 | BV9: =IF(BO9="overStocked",BL9,NA()) -> 146 | CA9: VoltSafe Power Bank 20k | CB9: 6806100 | CE9: others | CF9: =CE5-CF8 -> 14878578 | CX9: BlueWave Distributors
C10: profit | D10: =GETPIVOTDATA("Sum of Profit",$A$3) -> 8091717.5 | E10: =IF(D10>=1000000000, "$" & TEXT(D10/1000000000, "0.0") & "B", IF(D10>=1000000, "$" &TEXT(D10/1000000, "0.0") & "M", IF(D10>=1000, "$" &TEXT(D10/1000, "0.0") & "K", "$" &TEXT(D10, "0.0")))) -> $8.1M | F10: green | I10: Jun | J10: 6 | K10: Jun | L10: 2994527.5 | M10: 691147.5 | N10: =M10/L10 -> 0.23080352 | O10: =(L10-L9)/L9 -> 0.046079291 | Q10: Jun | S10: =IFERROR(MATCH(R21,K5:K16,0)-1,"No selection") -> No selection | AG10: Jun | AH10: 2994527.5 | AI10: 691147.5 | AJ10: 0.23080352 | AN10: Garki Market | AO10: 875462.5 | AP10: 4472122.5 | AQ10: =AO10/AP10 -> 0.19575996 | BI10: FreshDay Milk 1L | BJ10: 804540 | BK10: 149490 | BL10: 397 | BN10: =BK10/BJ10 -> 0.18580804 | BO10: =_xlfn.XLOOKUP(BI10,ProductMasterTable[Product Name],ProductMasterTable[Stock status],) -> underStocked | BP10: =BJ10 -> 804540 | BQ10: =IF(BO10="underStocked",BN10,NA()) -> 0.18580804 | BR10: =IF(BO10="underStocked",BL10,NA()) -> 397 | BS10: =IF(BO10="Health",BN10,NA()) -> #N/A | BT10: =IF(BO10="Health",BL10,NA()) -> #N/A | BU10: =IF(BO10="overStocked",BN10,NA()) -> #N/A | BV10: =IF(BO10="overStocked",BL10,NA()) -> #N/A | CO10: Total Losses Caused by Discounts | CX10: CarePlus Wholesale
C11: transaction | D11: =GETPIVOTDATA("Count of Product Name",$A$3) -> 2801 | E11: =IF(D11>=1000000000, "$" & TEXT(D11/1000000000, "0.0") & "B", IF(D11>=1000000, "$" &TEXT(D11/1000000, "0.0") & "M", IF(D11>=1000, "$" &TEXT(D11/1000, "0.0") & "K", "$" &TEXT(D11, "0.0")))) -> $2.8K | F11: blacke | I11: Jul | J11: 7 | K11: Jul | L11: 3453750 | M11: 671270 | N11: =M11/L11 -> 0.19435975 | O11: =(L11-L10)/L10 -> 0.15335391 | Q11: Jul | AG11: Jul | AH11: 3453750 | AI11: 671270 | AJ11: 0.19435975 | AN11: Kano Central | AO11: 715165 | AP11: 3453775 | AQ11: =AO11/AP11 -> 0.20706763 | BI11: FreshMint Toothpaste | BJ11: 755820 | BK11: 239820 | BL11: 430 | BN11: =BK11/BJ11 -> 0.31729777 | BO11: =_xlfn.XLOOKUP(BI11,ProductMasterTable[Product Name],ProductMasterTable[Stock status],) -> Health | BP11: =BJ11 -> 755820 | BQ11: =IF(BO11="underStocked",BN11,NA()) -> #N/A | BR11: =IF(BO11="underStocked",BL11,NA()) -> #N/A | BS11: =IF(BO11="Health",BN11,NA()) -> 0.31729777 | BT11: =IF(BO11="Health",BL11,NA()) -> 430 | BU11: =IF(BO11="overStocked",BN11,NA()) -> #N/A | BV11: =IF(BO11="overStocked",BL11,NA()) -> #N/A | CO11: =SUMIFS(Sales_Clean_Reference!X:X, Sales_Clean_Reference!X:X, "<0", Sales_Clean_Reference!Q:Q, ">0") -> -63805 | CX11: CleanHome Supply
C12: profit margin | D12: =D10/D9 -> 0.20349351 | E12: =IF(D12>=1000000000, "$" & TEXT(D12/1000000000, "0.0") & "B", IF(D12>=1000000, "$" &TEXT(D12/1000000, "0.0") & "M", IF(D12>=1000, "$" &TEXT(D12/1000, "0.0") & "K", "$" &TEXT(D12, "0.0")))) -> $0.2 | F12: pink | I12: Aug | J12: 8 | K12: Aug | L12: 3257970 | M12: 630800 | N12: =M12/L12 -> 0.1936175 | O12: =(L12-L11)/L11 -> -0.056686211 | Q12: Aug | AG12: Aug | AH12: 3257970 | AI12: 630800 | AJ12: 0.1936175 | AN12: Ilorin Retail | AO12: 511290 | AP12: 2735080 | AQ12: =AO12/AP12 -> 0.18693786 | BI12: GlowPlus Body Lotion | BJ12: 1285700 | BK12: 358200 | BL12: 265 | BN12: =BK12/BJ12 -> 0.2786031 | BO12: =_xlfn.XLOOKUP(BI12,ProductMasterTable[Product Name],ProductMasterTable[Stock status],) -> Health | BP12: =BJ12 -> 1285700 | BQ12: =IF(BO12="underStocked",BN12,NA()) -> #N/A | BR12: =IF(BO12="underStocked",BL12,NA()) -> #N/A | BS12: =IF(BO12="Health",BN12,NA()) -> 0.2786031 | BT12: =IF(BO12="Health",BL12,NA()) -> 265 | BU12: =IF(BO12="overStocked",BN12,NA()) -> #N/A | BV12: =IF(BO12="overStocked",BL12,NA()) -> #N/A | CO12: Number of Loss Transactions Due to Discounts | CT12: Transactions | CX12: Digital Market Supply
C13: total cost | D13: =GETPIVOTDATA("Sum of Total Cost",$A$3) -> 31672290 | E13: =IF(D13>=1000000000, "$" & TEXT(D13/1000000000, "0.0") & "B", IF(D13>=1000000, "$" &TEXT(D13/1000000, "0.0") & "M", IF(D13>=1000, "$" &TEXT(D13/1000, "0.0") & "K", "$" &TEXT(D13, "0.0")))) -> $31.7M | I13: Sep | J13: 9 | K13: Sep | L13: 3195660 | M13: 693190 | N13: =M13/L13 -> 0.21691607 | O13: =(L13-L12)/L12 -> -0.019125406 | Q13: Sep | S13: =COUNTA(Q5:Q16) -> 12 | AG13: Sep | AH13: 3195660 | AI13: 693190 | AJ13: 0.21691607 | AN13: avrege | AQ13: =AVERAGE(AQ5:AQ12) -> 0.20221908 | BI13: Golden Harvest Rice 5kg | BJ13: 7868875 | BK13: 865375 | BL13: 483 | BN13: =BK13/BJ13 -> 0.10997442 | BO13: =_xlfn.XLOOKUP(BI13,ProductMasterTable[Product Name],ProductMasterTable[Stock status],) -> underStocked | BP13: =BJ13 -> 7868875 | BQ13: =IF(BO13="underStocked",BN13,NA()) -> 0.10997442 | BR13: =IF(BO13="underStocked",BL13,NA()) -> 483 | BS13: =IF(BO13="Health",BN13,NA()) -> #N/A | BT13: =IF(BO13="Health",BL13,NA()) -> #N/A | BU13: =IF(BO13="overStocked",BN13,NA()) -> #N/A | BV13: =IF(BO13="overStocked",BL13,NA()) -> #N/A | CO13: =COUNTIFS(Sales_Clean_Reference!X:X, "<0", Sales_Clean_Reference!Q:Q, ">0") -> 48 | CT13: =COUNTA(Sales_Clean_Reference!A:A) -> 2802 | CX13: Everyday Essentials
C14: avg month Revenue | D14: =D9/12 -> 3313667.3 | E14: =IF(D14>=1000000000, "$" & TEXT(D14/1000000000, "0.0") & "B", IF(D14>=1000000, "$" &TEXT(D14/1000000, "0.0") & "M", IF(D14>=1000, "$" &TEXT(D14/1000, "0.0") & "K", "$" &TEXT(D14, "0.0")))) -> $3.3M | I14: Oct | J14: 10 | K14: Oct | L14: 3749885 | M14: 752445 | N14: =M14/L14 -> 0.20065815 | O14: =(L14-L13)/L13 -> 0.17343053 | Q14: Oct | AG14: Oct | AH14: 3749885 | AI14: 752445 | AJ14: 0.20065815 | BI14: HomeFresh Air Freshener | BJ14: 318240 | BK14: 90440 | BL14: 134 | BN14: =BK14/BJ14 -> 0.28418803 | BO14: =_xlfn.XLOOKUP(BI14,ProductMasterTable[Product Name],ProductMasterTable[Stock status],) -> overStocked | BP14: =BJ14 -> 318240 | BQ14: =IF(BO14="underStocked",BN14,NA()) -> #N/A | BR14: =IF(BO14="underStocked",BL14,NA()) -> #N/A | BS14: =IF(BO14="Health",BN14,NA()) -> #N/A | BT14: =IF(BO14="Health",BL14,NA()) -> #N/A | BU14: =IF(BO14="overStocked",BN14,NA()) -> 0.28418803 | BV14: =IF(BO14="overStocked",BL14,NA()) -> 134 | CO14: Percentage of Losing Orders Out of Total Sales | CX14: Metro Drinks
C15: AVG month Revenue | D15: =D9/D16 -> 3313667.3 | E15: =IF(D15>=1000000000, "$" & TEXT(D15/1000000000, "0.0") & "B", IF(D15>=1000000, "$" &TEXT(D15/1000000, "0.0") & "M", IF(D15>=1000, "$" &TEXT(D15/1000, "0.0") & "K", "$" &TEXT(D15, "0.0")))) -> $3.3M | I15: Nov | J15: 11 | K15: Nov | L15: 3305695 | M15: 666675 | N15: =M15/L15 -> 0.20167469 | O15: =(L15-L14)/L14 -> -0.1184543 | Q15: Nov | AG15: Nov | AH15: 3305695 | AI15: 666675 | AJ15: 0.20167469 | BI15: Luma LED Bulb 12W | BJ15: 977125 | BK15: 335125 | BL15: 428 | BN15: =BK15/BJ15 -> 0.34297045 | BO15: =_xlfn.XLOOKUP(BI15,ProductMasterTable[Product Name],ProductMasterTable[Stock status],) -> Health | BP15: =BJ15 -> 977125 | BQ15: =IF(BO15="underStocked",BN15,NA()) -> #N/A | BR15: =IF(BO15="underStocked",BL15,NA()) -> #N/A | BS15: =IF(BO15="Health",BN15,NA()) -> 0.34297045 | BT15: =IF(BO15="Health",BL15,NA()) -> 428 | BU15: =IF(BO15="overStocked",BN15,NA()) -> #N/A | BV15: =IF(BO15="overStocked",BL15,NA()) -> #N/A | CO15: =CO13/CT13 -> 0.017130621 | CX15: Metro Stationery
C16: count of month | D16: =COUNTA(I5:I16) -> 12 | E16: =IF(D16>=1000000000, "$" & TEXT(D16/1000000000, "0.0") & "B", IF(D16>=1000000, "$" &TEXT(D16/1000000, "0.0") & "M", IF(D16>=1000, "$" &TEXT(D16/1000, "0.0") & "K", "$" &TEXT(D16, "0.0")))) -> $12.0 | I16: Dec | J16: 12 | K16: Dec | L16: 3462140 | M16: 683580 | N16: =M16/L16 -> 0.19744436 | O16: =(L16-L15)/L15 -> 0.047325903 | Q16: Dec | AG16: Dec | AH16: 3462140 | AI16: 683580 | AJ16: 0.19744436 | AO16: =SUM(AO5:AO7)/SUM(AO5:AO12) -> 0.5057029 | AP16: =SUM(AP5:AP7)/SUM(AP5:AP12) -> 0.49814358 | BI16: Mama's Pride Beans 2kg | BJ16: 2005020 | BK16: 318620 | BL16: 272 | BN16: =BK16/BJ16 -> 0.15891113 | BO16: =_xlfn.XLOOKUP(BI16,ProductMasterTable[Product Name],ProductMasterTable[Stock status],) -> Health | BP16: =BJ16 -> 2005020 | BQ16: =IF(BO16="underStocked",BN16,NA()) -> #N/A | BR16: =IF(BO16="underStocked",BL16,NA()) -> #N/A | BS16: =IF(BO16="Health",BN16,NA()) -> 0.15891113 | BT16: =IF(BO16="Health",BL16,NA()) -> 272 | BU16: =IF(BO16="overStocked",BN16,NA()) -> #N/A | BV16: =IF(BO16="overStocked",BL16,NA()) -> #N/A | CS16: =100-1.7 -> 98.3 | CX16: NorthStar Foods
C17: AVG month profit | D17: =B4/D16 -> 674309.79 | E17: =IF(D17>=1000000000, "$" & TEXT(D17/1000000000, "0.0") & "B", IF(D17>=1000000, "$" &TEXT(D17/1000000, "0.0") & "M", IF(D17>=1000, "$" &TEXT(D17/1000, "0.0") & "K", "$" &TEXT(D17, "0.0")))) -> $674.3K | BI17: Naija Malt Can | BJ17: 442297.5 | BK17: 134297.5 | BL17: 560 | BN17: =BK17/BJ17 -> 0.30363613 | BO17: =_xlfn.XLOOKUP(BI17,ProductMasterTable[Product Name],ProductMasterTable[Stock status],) -> Health | BP17: =BJ17 -> 442297.5 | BQ17: =IF(BO17="underStocked",BN17,NA()) -> #N/A | BR17: =IF(BO17="underStocked",BL17,NA()) -> #N/A | BS17: =IF(BO17="Health",BN17,NA()) -> 0.30363613 | BT17: =IF(BO17="Health",BL17,NA()) -> 560 | BU17: =IF(BO17="overStocked",BN17,NA()) -> #N/A | BV17: =IF(BO17="overStocked",BL17,NA()) -> #N/A | CX17: OfficeSource Nigeria
BI18: OfficeMate A4 Paper | BJ18: 1046850 | BK18: 157650 | BL18: 171 | BN18: =BK18/BJ18 -> 0.15059464 | BO18: =_xlfn.XLOOKUP(BI18,ProductMasterTable[Product Name],ProductMasterTable[Stock status],) -> overStocked | BP18: =BJ18 -> 1046850 | BQ18: =IF(BO18="underStocked",BN18,NA()) -> #N/A | BR18: =IF(BO18="underStocked",BL18,NA()) -> #N/A | BS18: =IF(BO18="Health",BN18,NA()) -> #N/A | BT18: =IF(BO18="Health",BL18,NA()) -> #N/A | BU18: =IF(BO18="overStocked",BN18,NA()) -> 0.15059464 | BV18: =IF(BO18="overStocked",BL18,NA()) -> 171 | CX18: PaperLine Ltd
BI19: PowerMax Extension Box | BJ19: 1185450 | BK19: 195450 | BL19: 132 | BN19: =BK19/BJ19 -> 0.1648741 | BO19: =_xlfn.XLOOKUP(BI19,ProductMasterTable[Product Name],ProductMasterTable[Stock status],) -> Health | BP19: =BJ19 -> 1185450 | BQ19: =IF(BO19="underStocked",BN19,NA()) -> #N/A | BR19: =IF(BO19="underStocked",BL19,NA()) -> #N/A | BS19: =IF(BO19="Health",BN19,NA()) -> 0.1648741 | BT19: =IF(BO19="Health",BL19,NA()) -> 132 | BU19: =IF(BO19="overStocked",BN19,NA()) -> #N/A | BV19: =IF(BO19="overStocked",BL19,NA()) -> #N/A | CO19: Total Losses from All Negative Orders of profit | CX19: Prime Grocery Ltd
V20: profit | AA20: profit margin | BI20: RoyalScent Perfume 50ml | BJ20: 686250 | BK20: 150750 | BL20: 63 | BN20: =BK20/BJ20 -> 0.21967213 | BO20: =_xlfn.XLOOKUP(BI20,ProductMasterTable[Product Name],ProductMasterTable[Stock status],) -> overStocked | BP20: =BJ20 -> 686250 | BQ20: =IF(BO20="underStocked",BN20,NA()) -> #N/A | BR20: =IF(BO20="underStocked",BL20,NA()) -> #N/A | BS20: =IF(BO20="Health",BN20,NA()) -> #N/A | BT20: =IF(BO20="Health",BL20,NA()) -> #N/A | BU20: =IF(BO20="overStocked",BN20,NA()) -> 0.21967213 | BV20: =IF(BO20="overStocked",BL20,NA()) -> 63 | CO20: =SUMIF(Sales_Clean_Reference!X:X, "<0") -> -82655 | CX20: Refresh Nigeria
Q21: current month | R21: =IF(S7=1,Q5,"") | BI21: SilkyTouch Bath Soap | BJ21: 491767.5 | BK21: 152767.5 | BL21: 565 | BN21: =BK21/BJ21 -> 0.31064985 | BO21: =_xlfn.XLOOKUP(BI21,ProductMasterTable[Product Name],ProductMasterTable[Stock status],) -> Health | BP21: =BJ21 -> 491767.5 | BQ21: =IF(BO21="underStocked",BN21,NA()) -> #N/A | BR21: =IF(BO21="underStocked",BL21,NA()) -> #N/A | BS21: =IF(BO21="Health",BN21,NA()) -> 0.31064985 | BT21: =IF(BO21="Health",BL21,NA()) -> 565 | BU21: =IF(BO21="overStocked",BN21,NA()) -> #N/A | BV21: =IF(BO21="overStocked",BL21,NA()) -> #N/A | CP21: Total Net Profit | CX21: TechBridge Africa
Q22: prevous month | R22: =IFERROR(VLOOKUP(S10,J5:K16,2,0),"") | BI22: SoftCare Tissue 10 Rolls | BJ22: 1276650 | BK22: 313450 | BL22: 301 | BN22: =BK22/BJ22 -> 0.2455254 | BO22: =_xlfn.XLOOKUP(BI22,ProductMasterTable[Product Name],ProductMasterTable[Stock status],) -> Health | BP22: =BJ22 -> 1276650 | BQ22: =IF(BO22="underStocked",BN22,NA()) -> #N/A | BR22: =IF(BO22="underStocked",BL22,NA()) -> #N/A | BS22: =IF(BO22="Health",BN22,NA()) -> 0.2455254 | BT22: =IF(BO22="Health",BL22,NA()) -> 301 | BU22: =IF(BO22="overStocked",BN22,NA()) -> #N/A | BV22: =IF(BO22="overStocked",BL22,NA()) -> #N/A | CP22: =SUM(Sales_Clean_Reference!X:X) -> 8091717.5 | CX22: VoltEdge Ltd
BI23: SoundBeat Earbuds | BJ23: 3438225 | BK23: 900725 | BL23: 203 | BN23: =BK23/BJ23 -> 0.26197384 | BO23: =_xlfn.XLOOKUP(BI23,ProductMasterTable[Product Name],ProductMasterTable[Stock status],) -> underStocked | BP23: =BJ23 -> 3438225 | BQ23: =IF(BO23="underStocked",BN23,NA()) -> 0.26197384 | BR23: =IF(BO23="underStocked",BL23,NA()) -> 203 | BS23: =IF(BO23="Health",BN23,NA()) -> #N/A | BT23: =IF(BO23="Health",BL23,NA()) -> #N/A | BU23: =IF(BO23="overStocked",BN23,NA()) -> #N/A | BV23: =IF(BO23="overStocked",BL23,NA()) -> #N/A
Q24: current month revevue | R24: =IFERROR(VLOOKUP(R21,K5:L16,2,0),"select month") -> select month | V24: current month profit | W24: =VLOOKUP(R21,K5:M16,3,0) -> #N/A | X24: =IFERROR(IF(W24>=1000000000, "$" & TEXT(W24/1000000000, "0.0") & "B", IF(W24>=1000000, "$" &TEXT(W24/1000000, "0.0") & "M", IF(W24>=1000, "$" &TEXT(W24/1000, "0.0") & "K", "$" &TEXT(W24, "0.0")))),"") | AA24: current month p_margin | AB24: =VLOOKUP(R21,K5:N16,4,0) -> #N/A | BI24: Sparkle Cola 50cl | BJ24: 383542.5 | BK24: 136372.5 | BL24: 749 | BN24: =BK24/BJ24 -> 0.35556034 | BO24: =_xlfn.XLOOKUP(BI24,ProductMasterTable[Product Name],ProductMasterTable[Stock status],) -> Health | BP24: =BJ24 -> 383542.5 | BQ24: =IF(BO24="underStocked",BN24,NA()) -> #N/A | BR24: =IF(BO24="underStocked",BL24,NA()) -> #N/A | BS24: =IF(BO24="Health",BN24,NA()) -> 0.35556034 | BT24: =IF(BO24="Health",BL24,NA()) -> 749 | BU24: =IF(BO24="overStocked",BN24,NA()) -> #N/A | BV24: =IF(BO24="overStocked",BL24,NA()) -> #N/A | CP24: Discount loss as a percentage of total total losses
Q25: prevous month revevue | R25: =IFERROR(VLOOKUP(R22,K5:L16,2,0),"") | S25: =IFERROR(IF(R25>=1000000000, "$" & TEXT(R25/1000000000, "0.0") & "B", IF(R25>=1000000, "$" &TEXT(R25/1000000, "0.0") & "M", IF(R25>=1000, "$" &TEXT(R25/1000, "0.0") & "K", "$" &TEXT(R25, "0.0")))),"") | V25: pervous month profit | W25: =VLOOKUP(R22,K5:M16,3,0) -> #N/A | X25: =IFERROR(IF(W25>=1000000000, "$" & TEXT(W25/1000000000, "0.0") & "B", IF(W25>=1000000, "$" &TEXT(W25/1000000, "0.0") & "M", IF(W25>=1000, "$" &TEXT(W25/1000, "0.0") & "K", "$" &TEXT(W25, "0.0")))),"") | AA25: pervous month p-margin | AB25: =VLOOKUP(R22,K5:N16,4,0) -> #N/A | BI25: StudyPro Notebook Pack | BJ25: 1205820 | BK25: 346220 | BL25: 307 | BN25: =BK25/BJ25 -> 0.28712411 | BO25: =_xlfn.XLOOKUP(BI25,ProductMasterTable[Product Name],ProductMasterTable[Stock status],) -> underStocked | BP25: =BJ25 -> 1205820 | BQ25: =IF(BO25="underStocked",BN25,NA()) -> 0.28712411 | BR25: =IF(BO25="underStocked",BL25,NA()) -> 307 | BS25: =IF(BO25="Health",BN25,NA()) -> #N/A | BT25: =IF(BO25="Health",BL25,NA()) -> #N/A | BU25: =IF(BO25="overStocked",BN25,NA()) -> #N/A | BV25: =IF(BO25="overStocked",BL25,NA()) -> #N/A | CQ25: =CO11/CO20 -> 0.77194362
V26: mom change | W26: =IFERROR((W24-W25)/W25,"") | X26: =W26 | AA26: mom change | AB26: =IFERROR((AB24-AB25)/AB25,"") | AC26: =AB26 | BI26: SunGold Vegetable Oil 2L | BJ26: 4767210 | BK26: 695610 | BL26: 522 | BN26: =BK26/BJ26 -> 0.14591554 | BO26: =_xlfn.XLOOKUP(BI26,ProductMasterTable[Product Name],ProductMasterTable[Stock status],) -> underStocked | BP26: =BJ26 -> 4767210 | BQ26: =IF(BO26="underStocked",BN26,NA()) -> 0.14591554 | BR26: =IF(BO26="underStocked",BL26,NA()) -> 522 | BS26: =IF(BO26="Health",BN26,NA()) -> #N/A | BT26: =IF(BO26="Health",BL26,NA()) -> #N/A | BU26: =IF(BO26="overStocked",BN26,NA()) -> #N/A | BV26: =IF(BO26="overStocked",BL26,NA()) -> #N/A | CP26: Discount Loss % of Total Profit
Q27: mom change | R27: =(R24-R25)/R25 -> #VALUE! | S27: =IFERROR(IF(R27>0,T30&TEXT(R27,"0.0%"),T31&TEXT(R27,"0.0%")),"") | AB27: =VLOOKUP(R21,K5:O16,5,0) -> #N/A | BI27: VoltSafe Power Bank 20k | BJ27: 6806100 | BK27: 1442100 | BL27: 298 | BN27: =BK27/BJ27 -> 0.21188346 | BO27: =_xlfn.XLOOKUP(BI27,ProductMasterTable[Product Name],ProductMasterTable[Stock status],) -> underStocked | BP27: =BJ27 -> 6806100 | BQ27: =IF(BO27="underStocked",BN27,NA()) -> 0.21188346 | BR27: =IF(BO27="underStocked",BL27,NA()) -> 298 | BS27: =IF(BO27="Health",BN27,NA()) -> #N/A | BT27: =IF(BO27="Health",BL27,NA()) -> #N/A | BU27: =IF(BO27="overStocked",BN27,NA()) -> #N/A | BV27: =IF(BO27="overStocked",BL27,NA()) -> #N/A | CP27: =CO11/CP22 -> -0.0078852234
Q28: TITEL | R28: ="VS"&" " &R22 -> VS | BI28: WriteWell Pen Pack | BJ28: 617295 | BK28: 203895 | BL28: 318 | BO28: =_xlfn.XLOOKUP(BI28,ProductMasterTable[Product Name],ProductMasterTable[Stock status],) -> underStocked | BP28: =BJ28 -> 617295 | BQ28: =IF(BO28="underStocked",BN28,NA()) -> 0 | BR28: =IF(BO28="underStocked",BL28,NA()) -> 318 | BS28: =IF(BO28="Health",BN28,NA()) -> #N/A | BT28: =IF(BO28="Health",BL28,NA()) -> #N/A | BU28: =IF(BO28="overStocked",BN28,NA()) -> #N/A | BV28: =IF(BO28="overStocked",BL28,NA()) -> #N/A
S30: UP | T30: ▲
S31: DOWN | T31: ▼ | BN31: Average revenue | BO31: =AVERAGE(BP5:BP28) -> 1656833.6
BN32: Average profit margin | BO32: =AVERAGE(BN5:BN27) -> 0.25104255

Sheet dashboard

Sheet Data Dictionary
A1: Field | B1: Meaning | C1: Data Type | D1: Analyst Note
A2: Order ID | B2: Unique transaction identifier | C2: Text | D2: Check duplicates
A3: Order Date | B3: Date of sale | C3: Date | D3: Create Month and Year fields during analysis
A4: Product ID | B4: Unique product code | C4: Text | D4: Join to Product_Master
A5: Product Name | B5: Product description | C5: Text | D5: Some raw values should be validated against Product_Master
A6: Category | B6: High-level product group | C6: Text | D6: Some blanks exist in raw data
A7: Subcategory | B7: Detailed product group | C7: Text | D7: Use for drill-down
A8: Brand | B8: Product brand | C8: Text | D8: Use for product comparison
A9: Branch ID | B9: Unique branch code | C9: Text | D9: Join to Branch_Master
A10: Branch Name | B10: Retail branch | C10: Text | D10: Contains spaces or spelling issues in raw data
A11: State | B11: Nigerian state | C11: Text | D11: Geographic analysis
A12: Region | B12: Business region | C12: Text | D12: Contains inconsistent case in raw data
... A27: Inventory Status | B27: Understocked, Healthy or Overstocked | C27: Text | D27: Based on Closing Stock and Reorder Level

Sheet Business Questions
A1: Priority | B1: Business Question | C1: Recommended Analysis | D1: Suggested Visual
A2: Core | B2: Are sales increasing while profit margin is declining? | C2: Monthly Net Revenue, Profit and Profit Margin | D2: Combo or line chart
A3: Core | B3: Product opportunity matrix ( Revenue vs Margin) | C3: Revenue versus Profit share | D3: Scatter plot or ranked bar chart
A4: Core | B4: Which branches generate the strongest and weakest profitability? | C4: Revenue, Profit and Margin by Branch | D4: Clustered bar chart
A5: Core | B5: How much revenue is being sacrificed through discounts? | C5: Discount Amount and Profit Margin by Category | D5: Column chart
A6: Core | B6: Which products are understocked or overstocked? | C6: Closing Stock compared with Reorder Level | D6: Inventory status bar/table
A7: Core | B7: Which fast-selling products require urgent replenishment? | C7: Quantity Sold + Inventory Status | D7: Priority matrix
A8: Supporting | B8: Which customer type generates the highest profit? | C8: Revenue, Profit and Average Order Value by Customer Type | D8: Bar chart
A9: Supporting | B9: Which payment methods dominate each branch? | C9: Transaction count and Revenue by Payment Method | D9: 100% stacked column
A10: Supporting | B10: Which suppliers have long delivery times and understocked products? | C10: Average Delivery Days + Inventory Status | D10: Supplier risk table
A11: Supporting | B11: What is the value and frequency of product returns? | C11: Negative quantities by Product and Branch | D11: Bar chart
A12: Decision | B12: What three actions should management take immediately? | C12: Synthesis of evidence | D12: Recommendation cards
